versatyl/__init__.py
versatyl-0.0.1.dist-info/METADATA
versatyl-0.0.1.dist-info/WHEEL
versatyl-0.0.1.dist-info/top_level.txt
versatyl-0.0.1.dist-info/RECORD
