Metadata-Version: 2.4
Name: versatyl
Version: 0.0.1
Summary: wip
Author-email: Hans Gremmen <hans@leptonix.net>
License-Expression: MIT
Requires-Python: >=3.12
